{
  "realm": "deepion",
  "enabled": true,
  "sslRequired": "external",
  "registrationAllowed": false,
  "loginWithEmailAllowed": true,
  "accessTokenLifespan": 1800,
  "clients": [
    {
      "clientId": "deepion",
      "name": "Deep Ion DB",
      "enabled": true,
      "protocol": "openid-connect",
      "publicClient": true,
      "standardFlowEnabled": true,
      "directAccessGrantsEnabled": true,
      "redirectUris": ["http://localhost:4000/*"],
      "webOrigins": ["+"],
      "attributes": {
        "pkce.code.challenge.method": "S256"
      },
      "protocolMappers": [
        {
          "name": "deepion-audience",
          "protocol": "openid-connect",
          "protocolMapper": "oidc-audience-mapper",
          "consentRequired": false,
          "config": {
            "included.client.audience": "deepion",
            "id.token.claim": "false",
            "access.token.claim": "true"
          }
        }
      ]
    }
  ]
}
